<annotation verified="no">
  <folder>Re Sample documents</folder>
  <filename>7</filename>
  <path>C:\Users\maragathamani\Desktop\Re Sample documents\7.jpg</path>
  <source>
    <database>Unknown</database>
  </source>
  <size>
    <width>430</width>
    <height>538</height>
    <depth>1</depth>
  </size>
  <segmented>0</segmented>
  <object>
    <name>demo</name>
    <pose>Unspecified</pose>
    <truncated>0</truncated>
    <Difficult>0</Difficult>
    <bndbox>
      <xmin>154</xmin>
      <ymin>125</ymin>
      <xmax>283</xmax>
      <ymax>146</ymax>
    </bndbox>
  </object>
</annotation>
