<annotation verified="no">
  <folder>Re Sample documents</folder>
  <filename>9-02</filename>
  <path>C:\Users\maragathamani\Desktop\Re Sample documents\9-02.jpg</path>
  <source>
    <database>Unknown</database>
  </source>
  <size>
    <width>547</width>
    <height>472</height>
    <depth>1</depth>
  </size>
  <segmented>0</segmented>
  <object>
    <name>fax</name>
    <pose>Unspecified</pose>
    <truncated>0</truncated>
    <Difficult>0</Difficult>
    <bndbox>
      <xmin>44</xmin>
      <ymin>20</ymin>
      <xmax>193</xmax>
      <ymax>67</ymax>
    </bndbox>
  </object>
  <object>
    <name>fax</name>
    <pose>Unspecified</pose>
    <truncated>0</truncated>
    <Difficult>0</Difficult>
    <bndbox>
      <xmin>30</xmin>
      <ymin>199</ymin>
      <xmax>93</xmax>
      <ymax>215</ymax>
    </bndbox>
  </object>
</annotation>
